{
	"compactLayoutable" : true,
	"lookupLayoutable" : null,
	"recordTypeInfos" : [
                         {
                         "defaultRecordTypeMapping" : true,
                         "available" : true,
                         "recordTypeId" : "012000000000000AAA",
                         "urls" : {
                         "layout" : "\/services\/data\/v29.0\/sobjects\/Case\/describe\/layouts\/012000000000000AAA"
                         },
                         "name" : "Master"
                         }
                         ],
	"retrieveable" : true,
	"createable" : true,
	"undeletable" : false,
	"name" : "Case",
	"listviewable" : null,
	"keyPrefix" : "500",
	"customSetting" : false,
	"searchLayoutable" : true,
	"fields" : [
                {
                "byteLength" : 18,
                "scale" : 0,
                "unique" : false,
                "nillable" : false,
                "idLookup" : true,
                "sortable" : true,
                "inlineHelpText" : null,
                "relationshipName" : null,
                "soapType" : "tns:ID",
                "type" : "id",
                "externalId" : false,
                "calculated" : false,
                "calculatedFormula" : null,
                "restrictedDelete" : false,
                "htmlFormatted" : false,
                "createable" : false,
                "picklistValues" : [
				
                ],
                "controllerName" : null,
                "writeRequiresMasterRead" : false,
                "nameField" : false,
                "name" : "Id",
                "length" : 18,
                "digits" : 0,
                "defaultValue" : null,
                "autoNumber" : false,
                "custom" : false,
                "referenceTo" : [
				
                ],
                "precision" : 0,
                "updateable" : false,
                "permissionable" : false,
                "caseSensitive" : false,
                "relationshipOrder" : null,
                "label" : "Case ID",
                "deprecatedAndHidden" : false,
                "dependentPicklist" : false,
                "defaultValueFormula" : null,
                "cascadeDelete" : false,
                "filterable" : true,
                "namePointing" : false,
                "defaultedOnCreate" : true,
                "groupable" : true,
                "displayLocationInDecimal" : false,
                "restrictedPicklist" : false
                },
                {
                "byteLength" : 0,
                "scale" : 0,
                "unique" : false,
                "nillable" : false,
                "idLookup" : false,
                "sortable" : true,
                "inlineHelpText" : null,
                "relationshipName" : null,
                "soapType" : "xsd:boolean",
                "type" : "boolean",
                "externalId" : false,
                "calculated" : false,
                "calculatedFormula" : null,
                "restrictedDelete" : false,
                "htmlFormatted" : false,
                "createable" : false,
                "picklistValues" : [
				
                ],
                "controllerName" : null,
                "writeRequiresMasterRead" : false,
                "nameField" : false,
                "name" : "IsDeleted",
                "length" : 0,
                "digits" : 0,
                "defaultValue" : null,
                "autoNumber" : false,
                "custom" : false,
                "referenceTo" : [
				
                ],
                "precision" : 0,
                "updateable" : false,
                "permissionable" : false,
                "caseSensitive" : false,
                "relationshipOrder" : null,
                "label" : "Deleted",
                "deprecatedAndHidden" : false,
                "dependentPicklist" : false,
                "defaultValueFormula" : null,
                "cascadeDelete" : false,
                "filterable" : true,
                "namePointing" : false,
                "defaultedOnCreate" : true,
                "groupable" : true,
                "displayLocationInDecimal" : false,
                "restrictedPicklist" : false
                },
                {
                "byteLength" : 90,
                "scale" : 0,
                "unique" : false,
                "nillable" : false,
                "idLookup" : true,
                "sortable" : true,
                "inlineHelpText" : null,
                "relationshipName" : null,
                "soapType" : "xsd:string",
                "type" : "string",
                "externalId" : false,
                "calculated" : false,
                "calculatedFormula" : null,
                "restrictedDelete" : false,
                "htmlFormatted" : false,
                "createable" : false,
                "picklistValues" : [
				
                ],
                "controllerName" : null,
                "writeRequiresMasterRead" : false,
                "nameField" : true,
                "name" : "CaseNumber",
                "length" : 30,
                "digits" : 0,
                "defaultValue" : null,
                "autoNumber" : true,
                "custom" : false,
                "referenceTo" : [
				
                ],
                "precision" : 0,
                "updateable" : false,
                "permissionable" : false,
                "caseSensitive" : false,
                "relationshipOrder" : null,
                "label" : "Case Number",
                "deprecatedAndHidden" : false,
                "dependentPicklist" : false,
                "defaultValueFormula" : null,
                "cascadeDelete" : false,
                "filterable" : true,
                "namePointing" : false,
                "defaultedOnCreate" : true,
                "groupable" : false,
                "displayLocationInDecimal" : false,
                "restrictedPicklist" : false
                },
                {
                "byteLength" : 18,
                "scale" : 0,
                "unique" : false,
                "nillable" : true,
                "idLookup" : false,
                "sortable" : true,
                "inlineHelpText" : null,
                "relationshipName" : "Contact",
                "soapType" : "tns:ID",
                "type" : "reference",
                "externalId" : false,
                "calculated" : false,
                "calculatedFormula" : null,
                "restrictedDelete" : false,
                "htmlFormatted" : false,
                "createable" : true,
                "picklistValues" : [
				
                ],
                "controllerName" : null,
                "writeRequiresMasterRead" : false,
                "nameField" : false,
                "name" : "ContactId",
                "length" : 18,
                "digits" : 0,
                "defaultValue" : null,
                "autoNumber" : false,
                "custom" : false,
                "referenceTo" : [
                                 "Contact"
                                 ],
                "precision" : 0,
                "updateable" : true,
                "permissionable" : true,
                "caseSensitive" : false,
                "relationshipOrder" : null,
                "label" : "Contact ID",
                "deprecatedAndHidden" : false,
                "dependentPicklist" : false,
                "defaultValueFormula" : null,
                "cascadeDelete" : false,
                "filterable" : true,
                "namePointing" : false,
                "defaultedOnCreate" : false,
                "groupable" : true,
                "displayLocationInDecimal" : false,
                "restrictedPicklist" : false
                },
                {
                "byteLength" : 18,
                "scale" : 0,
                "unique" : false,
                "nillable" : true,
                "idLookup" : false,
                "sortable" : true,
                "inlineHelpText" : null,
                "relationshipName" : "Account",
                "soapType" : "tns:ID",
                "type" : "reference",
                "externalId" : false,
                "calculated" : false,
                "calculatedFormula" : null,
                "restrictedDelete" : false,
                "htmlFormatted" : false,
                "createable" : false,
                "picklistValues" : [
				
                ],
                "controllerName" : null,
                "writeRequiresMasterRead" : false,
                "nameField" : false,
                "name" : "AccountId",
                "length" : 18,
                "digits" : 0,
                "defaultValue" : null,
                "autoNumber" : false,
                "custom" : false,
                "referenceTo" : [
                                 "Account"
                                 ],
                "precision" : 0,
                "updateable" : false,
                "permissionable" : true,
                "caseSensitive" : false,
                "relationshipOrder" : null,
                "label" : "Account ID",
                "deprecatedAndHidden" : false,
                "dependentPicklist" : false,
                "defaultValueFormula" : null,
                "cascadeDelete" : false,
                "filterable" : true,
                "namePointing" : false,
                "defaultedOnCreate" : false,
                "groupable" : true,
                "displayLocationInDecimal" : false,
                "restrictedPicklist" : false
                },
                {
                "byteLength" : 18,
                "scale" : 0,
                "unique" : false,
                "nillable" : true,
                "idLookup" : false,
                "sortable" : true,
                "inlineHelpText" : null,
                "relationshipName" : "Parent",
                "soapType" : "tns:ID",
                "type" : "reference",
                "externalId" : false,
                "calculated" : false,
                "calculatedFormula" : null,
                "restrictedDelete" : false,
                "htmlFormatted" : false,
                "createable" : true,
                "picklistValues" : [
				
                ],
                "controllerName" : null,
                "writeRequiresMasterRead" : false,
                "nameField" : false,
                "name" : "ParentId",
                "length" : 18,
                "digits" : 0,
                "defaultValue" : null,
                "autoNumber" : false,
                "custom" : false,
                "referenceTo" : [
                                 "Case"
                                 ],
                "precision" : 0,
                "updateable" : true,
                "permissionable" : true,
                "caseSensitive" : false,
                "relationshipOrder" : null,
                "label" : "Parent Case ID",
                "deprecatedAndHidden" : false,
                "dependentPicklist" : false,
                "defaultValueFormula" : null,
                "cascadeDelete" : false,
                "filterable" : true,
                "namePointing" : false,
                "defaultedOnCreate" : false,
                "groupable" : true,
                "displayLocationInDecimal" : false,
                "restrictedPicklist" : false
                },
                {
                "byteLength" : 240,
                "scale" : 0,
                "unique" : false,
                "nillable" : true,
                "idLookup" : false,
                "sortable" : true,
                "inlineHelpText" : null,
                "relationshipName" : null,
                "soapType" : "xsd:string",
                "type" : "string",
                "externalId" : false,
                "calculated" : false,
                "calculatedFormula" : null,
                "restrictedDelete" : false,
                "htmlFormatted" : false,
                "createable" : false,
                "picklistValues" : [
				
                ],
                "controllerName" : null,
                "writeRequiresMasterRead" : false,
                "nameField" : false,
                "name" : "SuppliedName",
                "length" : 80,
                "digits" : 0,
                "defaultValue" : null,
                "autoNumber" : false,
                "custom" : false,
                "referenceTo" : [
				
                ],
                "precision" : 0,
                "updateable" : false,
                "permissionable" : true,
                "caseSensitive" : false,
                "relationshipOrder" : null,
                "label" : "Name",
                "deprecatedAndHidden" : false,
                "dependentPicklist" : false,
                "defaultValueFormula" : null,
                "cascadeDelete" : false,
                "filterable" : true,
                "namePointing" : false,
                "defaultedOnCreate" : false,
                "groupable" : true,
                "displayLocationInDecimal" : false,
                "restrictedPicklist" : false
                },
                {
                "byteLength" : 240,
                "scale" : 0,
                "unique" : false,
                "nillable" : true,
                "idLookup" : false,
                "sortable" : true,
                "inlineHelpText" : null,
                "relationshipName" : null,
                "soapType" : "xsd:string",
                "type" : "email",
                "externalId" : false,
                "calculated" : false,
                "calculatedFormula" : null,
                "restrictedDelete" : false,
                "htmlFormatted" : false,
                "createable" : false,
                "picklistValues" : [
				
                ],
                "controllerName" : null,
                "writeRequiresMasterRead" : false,
                "nameField" : false,
                "name" : "SuppliedEmail",
                "length" : 80,
                "digits" : 0,
                "defaultValue" : null,
                "autoNumber" : false,
                "custom" : false,
                "referenceTo" : [
				
                ],
                "precision" : 0,
                "updateable" : false,
                "permissionable" : true,
                "caseSensitive" : false,
                "relationshipOrder" : null,
                "label" : "Email Address",
                "deprecatedAndHidden" : false,
                "dependentPicklist" : false,
                "defaultValueFormula" : null,
                "cascadeDelete" : false,
                "filterable" : true,
                "namePointing" : false,
                "defaultedOnCreate" : false,
                "groupable" : true,
                "displayLocationInDecimal" : false,
                "restrictedPicklist" : false
                },
                {
                "byteLength" : 120,
                "scale" : 0,
                "unique" : false,
                "nillable" : true,
                "idLookup" : false,
                "sortable" : true,
                "inlineHelpText" : null,
                "relationshipName" : null,
                "soapType" : "xsd:string",
                "type" : "string",
                "externalId" : false,
                "calculated" : false,
                "calculatedFormula" : null,
                "restrictedDelete" : false,
                "htmlFormatted" : false,
                "createable" : false,
                "picklistValues" : [
				
                ],
                "controllerName" : null,
                "writeRequiresMasterRead" : false,
                "nameField" : false,
                "name" : "SuppliedPhone",
                "length" : 40,
                "digits" : 0,
                "defaultValue" : null,
                "autoNumber" : false,
                "custom" : false,
                "referenceTo" : [
				
                ],
                "precision" : 0,
                "updateable" : false,
                "permissionable" : true,
                "caseSensitive" : false,
                "relationshipOrder" : null,
                "label" : "Phone",
                "deprecatedAndHidden" : false,
                "dependentPicklist" : false,
                "defaultValueFormula" : null,
                "cascadeDelete" : false,
                "filterable" : true,
                "namePointing" : false,
                "defaultedOnCreate" : false,
                "groupable" : true,
                "displayLocationInDecimal" : false,
                "restrictedPicklist" : false
                },
                {
                "byteLength" : 240,
                "scale" : 0,
                "unique" : false,
                "nillable" : true,
                "idLookup" : false,
                "sortable" : true,
                "inlineHelpText" : null,
                "relationshipName" : null,
                "soapType" : "xsd:string",
                "type" : "string",
                "externalId" : false,
                "calculated" : false,
                "calculatedFormula" : null,
                "restrictedDelete" : false,
                "htmlFormatted" : false,
                "createable" : false,
                "picklistValues" : [
				
                ],
                "controllerName" : null,
                "writeRequiresMasterRead" : false,
                "nameField" : false,
                "name" : "SuppliedCompany",
                "length" : 80,
                "digits" : 0,
                "defaultValue" : null,
                "autoNumber" : false,
                "custom" : false,
                "referenceTo" : [
				
                ],
                "precision" : 0,
                "updateable" : false,
                "permissionable" : true,
                "caseSensitive" : false,
                "relationshipOrder" : null,
                "label" : "Company",
                "deprecatedAndHidden" : false,
                "dependentPicklist" : false,
                "defaultValueFormula" : null,
                "cascadeDelete" : false,
                "filterable" : true,
                "namePointing" : false,
                "defaultedOnCreate" : false,
                "groupable" : true,
                "displayLocationInDecimal" : false,
                "restrictedPicklist" : false
                },
                {
                "byteLength" : 120,
                "scale" : 0,
                "unique" : false,
                "nillable" : true,
                "idLookup" : false,
                "sortable" : true,
                "inlineHelpText" : null,
                "relationshipName" : null,
                "soapType" : "xsd:string",
                "type" : "picklist",
                "externalId" : false,
                "calculated" : false,
                "calculatedFormula" : null,
                "restrictedDelete" : false,
                "htmlFormatted" : false,
                "createable" : true,
                "picklistValues" : [
                                    {
                                    "value" : "Problem",
                                    "validFor" : null,
                                    "active" : true,
                                    "label" : "Problem",
                                    "defaultValue" : false
                                    },
                                    {
                                    "value" : "Feature Request",
                                    "validFor" : null,
                                    "active" : true,
                                    "label" : "Feature Request",
                                    "defaultValue" : false
                                    },
                                    {
                                    "value" : "Question",
                                    "validFor" : null,
                                    "active" : true,
                                    "label" : "Question",
                                    "defaultValue" : false
                                    }
                                    ],
                "controllerName" : null,
                "writeRequiresMasterRead" : false,
                "nameField" : false,
                "name" : "Type",
                "length" : 40,
                "digits" : 0,
                "defaultValue" : null,
                "autoNumber" : false,
                "custom" : false,
                "referenceTo" : [
				
                ],
                "precision" : 0,
                "updateable" : true,
                "permissionable" : true,
                "caseSensitive" : false,
                "relationshipOrder" : null,
                "label" : "Case Type",
                "deprecatedAndHidden" : false,
                "dependentPicklist" : false,
                "defaultValueFormula" : null,
                "cascadeDelete" : false,
                "filterable" : true,
                "namePointing" : false,
                "defaultedOnCreate" : false,
                "groupable" : true,
                "displayLocationInDecimal" : false,
                "restrictedPicklist" : false
                },
                {
                "byteLength" : 120,
                "scale" : 0,
                "unique" : false,
                "nillable" : true,
                "idLookup" : false,
                "sortable" : true,
                "inlineHelpText" : null,
                "relationshipName" : null,
                "soapType" : "xsd:string",
                "type" : "picklist",
                "externalId" : false,
                "calculated" : false,
                "calculatedFormula" : null,
                "restrictedDelete" : false,
                "htmlFormatted" : false,
                "createable" : true,
                "picklistValues" : [
                                    {
                                    "value" : "On Hold",
                                    "validFor" : null,
                                    "active" : true,
                                    "label" : "On Hold",
                                    "defaultValue" : false
                                    },
                                    {
                                    "value" : "Escalated",
                                    "validFor" : null,
                                    "active" : true,
                                    "label" : "Escalated",
                                    "defaultValue" : false
                                    },
                                    {
                                    "value" : "Closed",
                                    "validFor" : null,
                                    "active" : true,
                                    "label" : "Closed",
                                    "defaultValue" : false
                                    },
                                    {
                                    "value" : "New",
                                    "validFor" : null,
                                    "active" : true,
                                    "label" : "New",
                                    "defaultValue" : true
                                    }
                                    ],
                "controllerName" : null,
                "writeRequiresMasterRead" : false,
                "nameField" : false,
                "name" : "Status",
                "length" : 40,
                "digits" : 0,
                "defaultValue" : null,
                "autoNumber" : false,
                "custom" : false,
                "referenceTo" : [
				
                ],
                "precision" : 0,
                "updateable" : true,
                "permissionable" : false,
                "caseSensitive" : false,
                "relationshipOrder" : null,
                "label" : "Status",
                "deprecatedAndHidden" : false,
                "dependentPicklist" : false,
                "defaultValueFormula" : null,
                "cascadeDelete" : false,
                "filterable" : true,
                "namePointing" : false,
                "defaultedOnCreate" : true,
                "groupable" : true,
                "displayLocationInDecimal" : false,
                "restrictedPicklist" : false
                },
                {
                "byteLength" : 120,
                "scale" : 0,
                "unique" : false,
                "nillable" : true,
                "idLookup" : false,
                "sortable" : true,
                "inlineHelpText" : null,
                "relationshipName" : null,
                "soapType" : "xsd:string",
                "type" : "picklist",
                "externalId" : false,
                "calculated" : false,
                "calculatedFormula" : null,
                "restrictedDelete" : false,
                "htmlFormatted" : false,
                "createable" : true,
                "picklistValues" : [
                                    {
                                    "value" : "User didn't attend training",
                                    "validFor" : null,
                                    "active" : true,
                                    "label" : "User didn't attend training",
                                    "defaultValue" : false
                                    },
                                    {
                                    "value" : "Complex functionality",
                                    "validFor" : null,
                                    "active" : true,
                                    "label" : "Complex functionality",
                                    "defaultValue" : false
                                    },
                                    {
                                    "value" : "Existing problem",
                                    "validFor" : null,
                                    "active" : true,
                                    "label" : "Existing problem",
                                    "defaultValue" : false
                                    },
                                    {
                                    "value" : "Instructions not clear",
                                    "validFor" : null,
                                    "active" : true,
                                    "label" : "Instructions not clear",
                                    "defaultValue" : false
                                    },
                                    {
                                    "value" : "New problem",
                                    "validFor" : null,
                                    "active" : true,
                                    "label" : "New problem",
                                    "defaultValue" : false
                                    }
                                    ],
                "controllerName" : null,
                "writeRequiresMasterRead" : false,
                "nameField" : false,
                "name" : "Reason",
                "length" : 40,
                "digits" : 0,
                "defaultValue" : null,
                "autoNumber" : false,
                "custom" : false,
                "referenceTo" : [
				
                ],
                "precision" : 0,
                "updateable" : true,
                "permissionable" : true,
                "caseSensitive" : false,
                "relationshipOrder" : null,
                "label" : "Case Reason",
                "deprecatedAndHidden" : false,
                "dependentPicklist" : false,
                "defaultValueFormula" : null,
                "cascadeDelete" : false,
                "filterable" : true,
                "namePointing" : false,
                "defaultedOnCreate" : false,
                "groupable" : true,
                "displayLocationInDecimal" : false,
                "restrictedPicklist" : false
                },
                {
                "byteLength" : 120,
                "scale" : 0,
                "unique" : false,
                "nillable" : true,
                "idLookup" : false,
                "sortable" : true,
                "inlineHelpText" : null,
                "relationshipName" : null,
                "soapType" : "xsd:string",
                "type" : "picklist",
                "externalId" : false,
                "calculated" : false,
                "calculatedFormula" : null,
                "restrictedDelete" : false,
                "htmlFormatted" : false,
                "createable" : true,
                "picklistValues" : [
                                    {
                                    "value" : "Email",
                                    "validFor" : null,
                                    "active" : true,
                                    "label" : "Email",
                                    "defaultValue" : false
                                    },
                                    {
                                    "value" : "Phone",
                                    "validFor" : null,
                                    "active" : true,
                                    "label" : "Phone",
                                    "defaultValue" : false
                                    },
                                    {
                                    "value" : "Web",
                                    "validFor" : null,
                                    "active" : true,
                                    "label" : "Web",
                                    "defaultValue" : false
                                    }
                                    ],
                "controllerName" : null,
                "writeRequiresMasterRead" : false,
                "nameField" : false,
                "name" : "Origin",
                "length" : 40,
                "digits" : 0,
                "defaultValue" : null,
                "autoNumber" : false,
                "custom" : false,
                "referenceTo" : [
				
                ],
                "precision" : 0,
                "updateable" : true,
                "permissionable" : true,
                "caseSensitive" : false,
                "relationshipOrder" : null,
                "label" : "Case Origin",
                "deprecatedAndHidden" : false,
                "dependentPicklist" : false,
                "defaultValueFormula" : null,
                "cascadeDelete" : false,
                "filterable" : true,
                "namePointing" : false,
                "defaultedOnCreate" : false,
                "groupable" : true,
                "displayLocationInDecimal" : false,
                "restrictedPicklist" : false
                },
                {
                "byteLength" : 765,
                "scale" : 0,
                "unique" : false,
                "nillable" : true,
                "idLookup" : false,
                "sortable" : true,
                "inlineHelpText" : null,
                "relationshipName" : null,
                "soapType" : "xsd:string",
                "type" : "string",
                "externalId" : false,
                "calculated" : false,
                "calculatedFormula" : null,
                "restrictedDelete" : false,
                "htmlFormatted" : false,
                "createable" : true,
                "picklistValues" : [
				
                ],
                "controllerName" : null,
                "writeRequiresMasterRead" : false,
                "nameField" : false,
                "name" : "Subject",
                "length" : 255,
                "digits" : 0,
                "defaultValue" : null,
                "autoNumber" : false,
                "custom" : false,
                "referenceTo" : [
				
                ],
                "precision" : 0,
                "updateable" : true,
                "permissionable" : true,
                "caseSensitive" : false,
                "relationshipOrder" : null,
                "label" : "Subject",
                "deprecatedAndHidden" : false,
                "dependentPicklist" : false,
                "defaultValueFormula" : null,
                "cascadeDelete" : false,
                "filterable" : true,
                "namePointing" : false,
                "defaultedOnCreate" : false,
                "groupable" : true,
                "displayLocationInDecimal" : false,
                "restrictedPicklist" : false
                },
                {
                "byteLength" : 120,
                "scale" : 0,
                "unique" : false,
                "nillable" : true,
                "idLookup" : false,
                "sortable" : true,
                "inlineHelpText" : null,
                "relationshipName" : null,
                "soapType" : "xsd:string",
                "type" : "picklist",
                "externalId" : false,
                "calculated" : false,
                "calculatedFormula" : null,
                "restrictedDelete" : false,
                "htmlFormatted" : false,
                "createable" : true,
                "picklistValues" : [
                                    {
                                    "value" : "High",
                                    "validFor" : null,
                                    "active" : true,
                                    "label" : "High",
                                    "defaultValue" : false
                                    },
                                    {
                                    "value" : "Medium",
                                    "validFor" : null,
                                    "active" : true,
                                    "label" : "Medium",
                                    "defaultValue" : true
                                    },
                                    {
                                    "value" : "Low",
                                    "validFor" : null,
                                    "active" : true,
                                    "label" : "Low",
                                    "defaultValue" : false
                                    }
                                    ],
                "controllerName" : null,
                "writeRequiresMasterRead" : false,
                "nameField" : false,
                "name" : "Priority",
                "length" : 40,
                "digits" : 0,
                "defaultValue" : null,
                "autoNumber" : false,
                "custom" : false,
                "referenceTo" : [
				
                ],
                "precision" : 0,
                "updateable" : true,
                "permissionable" : true,
                "caseSensitive" : false,
                "relationshipOrder" : null,
                "label" : "Priority",
                "deprecatedAndHidden" : false,
                "dependentPicklist" : false,
                "defaultValueFormula" : null,
                "cascadeDelete" : false,
                "filterable" : true,
                "namePointing" : false,
                "defaultedOnCreate" : false,
                "groupable" : true,
                "displayLocationInDecimal" : false,
                "restrictedPicklist" : false
                },
                {
                "byteLength" : 96000,
                "scale" : 0,
                "unique" : false,
                "nillable" : true,
                "idLookup" : false,
                "sortable" : false,
                "inlineHelpText" : null,
                "relationshipName" : null,
                "soapType" : "xsd:string",
                "type" : "textarea",
                "externalId" : false,
                "calculated" : false,
                "calculatedFormula" : null,
                "restrictedDelete" : false,
                "htmlFormatted" : false,
                "createable" : true,
                "picklistValues" : [
				
                ],
                "controllerName" : null,
                "writeRequiresMasterRead" : false,
                "nameField" : false,
                "name" : "Description",
                "length" : 32000,
                "digits" : 0,
                "defaultValue" : null,
                "autoNumber" : false,
                "custom" : false,
                "referenceTo" : [
				
                ],
                "precision" : 0,
                "updateable" : true,
                "permissionable" : true,
                "caseSensitive" : false,
                "relationshipOrder" : null,
                "label" : "Description",
                "deprecatedAndHidden" : false,
                "dependentPicklist" : false,
                "defaultValueFormula" : null,
                "cascadeDelete" : false,
                "filterable" : false,
                "namePointing" : false,
                "defaultedOnCreate" : false,
                "groupable" : false,
                "displayLocationInDecimal" : false,
                "restrictedPicklist" : false
                },
                {
                "byteLength" : 0,
                "scale" : 0,
                "unique" : false,
                "nillable" : false,
                "idLookup" : false,
                "sortable" : true,
                "inlineHelpText" : null,
                "relationshipName" : null,
                "soapType" : "xsd:boolean",
                "type" : "boolean",
                "externalId" : false,
                "calculated" : false,
                "calculatedFormula" : null,
                "restrictedDelete" : false,
                "htmlFormatted" : false,
                "createable" : false,
                "picklistValues" : [
				
                ],
                "controllerName" : null,
                "writeRequiresMasterRead" : false,
                "nameField" : false,
                "name" : "IsClosed",
                "length" : 0,
                "digits" : 0,
                "defaultValue" : null,
                "autoNumber" : false,
                "custom" : false,
                "referenceTo" : [
				
                ],
                "precision" : 0,
                "updateable" : false,
                "permissionable" : false,
                "caseSensitive" : false,
                "relationshipOrder" : null,
                "label" : "Closed",
                "deprecatedAndHidden" : false,
                "dependentPicklist" : false,
                "defaultValueFormula" : null,
                "cascadeDelete" : false,
                "filterable" : true,
                "namePointing" : false,
                "defaultedOnCreate" : true,
                "groupable" : true,
                "displayLocationInDecimal" : false,
                "restrictedPicklist" : false
                },
                {
                "byteLength" : 0,
                "scale" : 0,
                "unique" : false,
                "nillable" : true,
                "idLookup" : false,
                "sortable" : true,
                "inlineHelpText" : null,
                "relationshipName" : null,
                "soapType" : "xsd:dateTime",
                "type" : "datetime",
                "externalId" : false,
                "calculated" : false,
                "calculatedFormula" : null,
                "restrictedDelete" : false,
                "htmlFormatted" : false,
                "createable" : false,
                "picklistValues" : [
				
                ],
                "controllerName" : null,
                "writeRequiresMasterRead" : false,
                "nameField" : false,
                "name" : "ClosedDate",
                "length" : 0,
                "digits" : 0,
                "defaultValue" : null,
                "autoNumber" : false,
                "custom" : false,
                "referenceTo" : [
				
                ],
                "precision" : 0,
                "updateable" : false,
                "permissionable" : true,
                "caseSensitive" : false,
                "relationshipOrder" : null,
                "label" : "Closed Date",
                "deprecatedAndHidden" : false,
                "dependentPicklist" : false,
                "defaultValueFormula" : null,
                "cascadeDelete" : false,
                "filterable" : true,
                "namePointing" : false,
                "defaultedOnCreate" : false,
                "groupable" : false,
                "displayLocationInDecimal" : false,
                "restrictedPicklist" : false
                },
                {
                "byteLength" : 0,
                "scale" : 0,
                "unique" : false,
                "nillable" : false,
                "idLookup" : false,
                "sortable" : true,
                "inlineHelpText" : null,
                "relationshipName" : null,
                "soapType" : "xsd:boolean",
                "type" : "boolean",
                "externalId" : false,
                "calculated" : false,
                "calculatedFormula" : null,
                "restrictedDelete" : false,
                "htmlFormatted" : false,
                "createable" : false,
                "picklistValues" : [
				
                ],
                "controllerName" : null,
                "writeRequiresMasterRead" : false,
                "nameField" : false,
                "name" : "IsEscalated",
                "length" : 0,
                "digits" : 0,
                "defaultValue" : null,
                "autoNumber" : false,
                "custom" : false,
                "referenceTo" : [
				
                ],
                "precision" : 0,
                "updateable" : false,
                "permissionable" : true,
                "caseSensitive" : false,
                "relationshipOrder" : null,
                "label" : "Escalated",
                "deprecatedAndHidden" : false,
                "dependentPicklist" : false,
                "defaultValueFormula" : null,
                "cascadeDelete" : false,
                "filterable" : true,
                "namePointing" : false,
                "defaultedOnCreate" : true,
                "groupable" : true,
                "displayLocationInDecimal" : false,
                "restrictedPicklist" : false
                },
                {
                "byteLength" : 18,
                "scale" : 0,
                "unique" : false,
                "nillable" : false,
                "idLookup" : false,
                "sortable" : true,
                "inlineHelpText" : null,
                "relationshipName" : "Owner",
                "soapType" : "tns:ID",
                "type" : "reference",
                "externalId" : false,
                "calculated" : false,
                "calculatedFormula" : null,
                "restrictedDelete" : false,
                "htmlFormatted" : false,
                "createable" : true,
                "picklistValues" : [
				
                ],
                "controllerName" : null,
                "writeRequiresMasterRead" : false,
                "nameField" : false,
                "name" : "OwnerId",
                "length" : 18,
                "digits" : 0,
                "defaultValue" : null,
                "autoNumber" : false,
                "custom" : false,
                "referenceTo" : [
                                 "Group",
                                 "User"
                                 ],
                "precision" : 0,
                "updateable" : true,
                "permissionable" : false,
                "caseSensitive" : false,
                "relationshipOrder" : null,
                "label" : "Owner ID",
                "deprecatedAndHidden" : false,
                "dependentPicklist" : false,
                "defaultValueFormula" : null,
                "cascadeDelete" : false,
                "filterable" : true,
                "namePointing" : true,
                "defaultedOnCreate" : true,
                "groupable" : true,
                "displayLocationInDecimal" : false,
                "restrictedPicklist" : false
                },
                {
                "byteLength" : 0,
                "scale" : 0,
                "unique" : false,
                "nillable" : false,
                "idLookup" : false,
                "sortable" : true,
                "inlineHelpText" : null,
                "relationshipName" : null,
                "soapType" : "xsd:dateTime",
                "type" : "datetime",
                "externalId" : false,
                "calculated" : false,
                "calculatedFormula" : null,
                "restrictedDelete" : false,
                "htmlFormatted" : false,
                "createable" : false,
                "picklistValues" : [
				
                ],
                "controllerName" : null,
                "writeRequiresMasterRead" : false,
                "nameField" : false,
                "name" : "CreatedDate",
                "length" : 0,
                "digits" : 0,
                "defaultValue" : null,
                "autoNumber" : false,
                "custom" : false,
                "referenceTo" : [
				
                ],
                "precision" : 0,
                "updateable" : false,
                "permissionable" : false,
                "caseSensitive" : false,
                "relationshipOrder" : null,
                "label" : "Created Date",
                "deprecatedAndHidden" : false,
                "dependentPicklist" : false,
                "defaultValueFormula" : null,
                "cascadeDelete" : false,
                "filterable" : true,
                "namePointing" : false,
                "defaultedOnCreate" : true,
                "groupable" : false,
                "displayLocationInDecimal" : false,
                "restrictedPicklist" : false
                },
                {
                "byteLength" : 18,
                "scale" : 0,
                "unique" : false,
                "nillable" : false,
                "idLookup" : false,
                "sortable" : true,
                "inlineHelpText" : null,
                "relationshipName" : "CreatedBy",
                "soapType" : "tns:ID",
                "type" : "reference",
                "externalId" : false,
                "calculated" : false,
                "calculatedFormula" : null,
                "restrictedDelete" : false,
                "htmlFormatted" : false,
                "createable" : false,
                "picklistValues" : [
				
                ],
                "controllerName" : null,
                "writeRequiresMasterRead" : false,
                "nameField" : false,
                "name" : "CreatedById",
                "length" : 18,
                "digits" : 0,
                "defaultValue" : null,
                "autoNumber" : false,
                "custom" : false,
                "referenceTo" : [
                                 "User"
                                 ],
                "precision" : 0,
                "updateable" : false,
                "permissionable" : false,
                "caseSensitive" : false,
                "relationshipOrder" : null,
                "label" : "Created By ID",
                "deprecatedAndHidden" : false,
                "dependentPicklist" : false,
                "defaultValueFormula" : null,
                "cascadeDelete" : false,
                "filterable" : true,
                "namePointing" : false,
                "defaultedOnCreate" : true,
                "groupable" : true,
                "displayLocationInDecimal" : false,
                "restrictedPicklist" : false
                },
                {
                "byteLength" : 0,
                "scale" : 0,
                "unique" : false,
                "nillable" : false,
                "idLookup" : false,
                "sortable" : true,
                "inlineHelpText" : null,
                "relationshipName" : null,
                "soapType" : "xsd:dateTime",
                "type" : "datetime",
                "externalId" : false,
                "calculated" : false,
                "calculatedFormula" : null,
                "restrictedDelete" : false,
                "htmlFormatted" : false,
                "createable" : false,
                "picklistValues" : [
				
                ],
                "controllerName" : null,
                "writeRequiresMasterRead" : false,
                "nameField" : false,
                "name" : "LastModifiedDate",
                "length" : 0,
                "digits" : 0,
                "defaultValue" : null,
                "autoNumber" : false,
                "custom" : false,
                "referenceTo" : [
				
                ],
                "precision" : 0,
                "updateable" : false,
                "permissionable" : false,
                "caseSensitive" : false,
                "relationshipOrder" : null,
                "label" : "Last Modified Date",
                "deprecatedAndHidden" : false,
                "dependentPicklist" : false,
                "defaultValueFormula" : null,
                "cascadeDelete" : false,
                "filterable" : true,
                "namePointing" : false,
                "defaultedOnCreate" : true,
                "groupable" : false,
                "displayLocationInDecimal" : false,
                "restrictedPicklist" : false
                },
                {
                "byteLength" : 18,
                "scale" : 0,
                "unique" : false,
                "nillable" : false,
                "idLookup" : false,
                "sortable" : true,
                "inlineHelpText" : null,
                "relationshipName" : "LastModifiedBy",
                "soapType" : "tns:ID",
                "type" : "reference",
                "externalId" : false,
                "calculated" : false,
                "calculatedFormula" : null,
                "restrictedDelete" : false,
                "htmlFormatted" : false,
                "createable" : false,
                "picklistValues" : [
				
                ],
                "controllerName" : null,
                "writeRequiresMasterRead" : false,
                "nameField" : false,
                "name" : "LastModifiedById",
                "length" : 18,
                "digits" : 0,
                "defaultValue" : null,
                "autoNumber" : false,
                "custom" : false,
                "referenceTo" : [
                                 "User"
                                 ],
                "precision" : 0,
                "updateable" : false,
                "permissionable" : false,
                "caseSensitive" : false,
                "relationshipOrder" : null,
                "label" : "Last Modified By ID",
                "deprecatedAndHidden" : false,
                "dependentPicklist" : false,
                "defaultValueFormula" : null,
                "cascadeDelete" : false,
                "filterable" : true,
                "namePointing" : false,
                "defaultedOnCreate" : true,
                "groupable" : true,
                "displayLocationInDecimal" : false,
                "restrictedPicklist" : false
                },
                {
                "byteLength" : 0,
                "scale" : 0,
                "unique" : false,
                "nillable" : false,
                "idLookup" : false,
                "sortable" : true,
                "inlineHelpText" : null,
                "relationshipName" : null,
                "soapType" : "xsd:dateTime",
                "type" : "datetime",
                "externalId" : false,
                "calculated" : false,
                "calculatedFormula" : null,
                "restrictedDelete" : false,
                "htmlFormatted" : false,
                "createable" : false,
                "picklistValues" : [
				
                ],
                "controllerName" : null,
                "writeRequiresMasterRead" : false,
                "nameField" : false,
                "name" : "SystemModstamp",
                "length" : 0,
                "digits" : 0,
                "defaultValue" : null,
                "autoNumber" : false,
                "custom" : false,
                "referenceTo" : [
				
                ],
                "precision" : 0,
                "updateable" : false,
                "permissionable" : false,
                "caseSensitive" : false,
                "relationshipOrder" : null,
                "label" : "System Modstamp",
                "deprecatedAndHidden" : false,
                "dependentPicklist" : false,
                "defaultValueFormula" : null,
                "cascadeDelete" : false,
                "filterable" : true,
                "namePointing" : false,
                "defaultedOnCreate" : true,
                "groupable" : false,
                "displayLocationInDecimal" : false,
                "restrictedPicklist" : false
                },
                {
                "byteLength" : 0,
                "scale" : 0,
                "unique" : false,
                "nillable" : true,
                "idLookup" : false,
                "sortable" : true,
                "inlineHelpText" : null,
                "relationshipName" : null,
                "soapType" : "xsd:dateTime",
                "type" : "datetime",
                "externalId" : false,
                "calculated" : false,
                "calculatedFormula" : null,
                "restrictedDelete" : false,
                "htmlFormatted" : false,
                "createable" : false,
                "picklistValues" : [
				
                ],
                "controllerName" : null,
                "writeRequiresMasterRead" : false,
                "nameField" : false,
                "name" : "LastViewedDate",
                "length" : 0,
                "digits" : 0,
                "defaultValue" : null,
                "autoNumber" : false,
                "custom" : false,
                "referenceTo" : [
				
                ],
                "precision" : 0,
                "updateable" : false,
                "permissionable" : false,
                "caseSensitive" : false,
                "relationshipOrder" : null,
                "label" : "Last Viewed Date",
                "deprecatedAndHidden" : false,
                "dependentPicklist" : false,
                "defaultValueFormula" : null,
                "cascadeDelete" : false,
                "filterable" : true,
                "namePointing" : false,
                "defaultedOnCreate" : false,
                "groupable" : false,
                "displayLocationInDecimal" : false,
                "restrictedPicklist" : false
                },
                {
                "byteLength" : 0,
                "scale" : 0,
                "unique" : false,
                "nillable" : true,
                "idLookup" : false,
                "sortable" : true,
                "inlineHelpText" : null,
                "relationshipName" : null,
                "soapType" : "xsd:dateTime",
                "type" : "datetime",
                "externalId" : false,
                "calculated" : false,
                "calculatedFormula" : null,
                "restrictedDelete" : false,
                "htmlFormatted" : false,
                "createable" : false,
                "picklistValues" : [
				
                ],
                "controllerName" : null,
                "writeRequiresMasterRead" : false,
                "nameField" : false,
                "name" : "LastReferencedDate",
                "length" : 0,
                "digits" : 0,
                "defaultValue" : null,
                "autoNumber" : false,
                "custom" : false,
                "referenceTo" : [
				
                ],
                "precision" : 0,
                "updateable" : false,
                "permissionable" : false,
                "caseSensitive" : false,
                "relationshipOrder" : null,
                "label" : "Last Referenced Date",
                "deprecatedAndHidden" : false,
                "dependentPicklist" : false,
                "defaultValueFormula" : null,
                "cascadeDelete" : false,
                "filterable" : true,
                "namePointing" : false,
                "defaultedOnCreate" : false,
                "groupable" : false,
                "displayLocationInDecimal" : false,
                "restrictedPicklist" : false
                }
                ],
	"custom" : false,
	"childRelationships" : [
                            {
                            "field" : "WhatId",
                            "childSObject" : "ActivityHistory",
                            "restrictedDelete" : false,
                            "relationshipName" : "ActivityHistories",
                            "deprecatedAndHidden" : false,
                            "cascadeDelete" : true
                            },
                            {
                            "field" : "LinkedEntityId",
                            "childSObject" : "AttachedContentDocument",
                            "restrictedDelete" : false,
                            "relationshipName" : "AttachedContentDocuments",
                            "deprecatedAndHidden" : false,
                            "cascadeDelete" : true
                            },
                            {
                            "field" : "ParentId",
                            "childSObject" : "Attachment",
                            "restrictedDelete" : false,
                            "relationshipName" : "Attachments",
                            "deprecatedAndHidden" : false,
                            "cascadeDelete" : true
                            },
                            {
                            "field" : "ParentId",
                            "childSObject" : "Case",
                            "restrictedDelete" : false,
                            "relationshipName" : "Cases",
                            "deprecatedAndHidden" : false,
                            "cascadeDelete" : false
                            },
                            {
                            "field" : "ParentId",
                            "childSObject" : "CaseComment",
                            "restrictedDelete" : false,
                            "relationshipName" : "CaseComments",
                            "deprecatedAndHidden" : false,
                            "cascadeDelete" : true
                            },
                            {
                            "field" : "CasesId",
                            "childSObject" : "CaseContactRole",
                            "restrictedDelete" : false,
                            "relationshipName" : "CaseContactRoles",
                            "deprecatedAndHidden" : false,
                            "cascadeDelete" : true
                            },
                            {
                            "field" : "ParentId",
                            "childSObject" : "CaseFeed",
                            "restrictedDelete" : false,
                            "relationshipName" : "Feeds",
                            "deprecatedAndHidden" : false,
                            "cascadeDelete" : true
                            },
                            {
                            "field" : "CaseId",
                            "childSObject" : "CaseHistory",
                            "restrictedDelete" : false,
                            "relationshipName" : "Histories",
                            "deprecatedAndHidden" : false,
                            "cascadeDelete" : true
                            },
                            {
                            "field" : "CaseId",
                            "childSObject" : "CaseShare",
                            "restrictedDelete" : false,
                            "relationshipName" : "Shares",
                            "deprecatedAndHidden" : false,
                            "cascadeDelete" : true
                            },
                            {
                            "field" : "CaseId",
                            "childSObject" : "CaseSolution",
                            "restrictedDelete" : false,
                            "relationshipName" : "CaseSolutions",
                            "deprecatedAndHidden" : false,
                            "cascadeDelete" : true
                            },
                            {
                            "field" : "ParentId",
                            "childSObject" : "CaseTeamMember",
                            "restrictedDelete" : false,
                            "relationshipName" : "TeamMembers",
                            "deprecatedAndHidden" : false,
                            "cascadeDelete" : true
                            },
                            {
                            "field" : "ParentId",
                            "childSObject" : "CaseTeamTemplateRecord",
                            "restrictedDelete" : false,
                            "relationshipName" : "TeamTemplateRecords",
                            "deprecatedAndHidden" : false,
                            "cascadeDelete" : true
                            },
                            {
                            "field" : "ParentId",
                            "childSObject" : "CombinedAttachment",
                            "restrictedDelete" : false,
                            "relationshipName" : "CombinedAttachments",
                            "deprecatedAndHidden" : false,
                            "cascadeDelete" : true
                            },
                            {
                            "field" : "LinkedEntityId",
                            "childSObject" : "ContentDocumentLink",
                            "restrictedDelete" : false,
                            "relationshipName" : null,
                            "deprecatedAndHidden" : false,
                            "cascadeDelete" : true
                            },
                            {
                            "field" : "FirstPublishLocationId",
                            "childSObject" : "ContentVersion",
                            "restrictedDelete" : false,
                            "relationshipName" : null,
                            "deprecatedAndHidden" : false,
                            "cascadeDelete" : false
                            },
                            {
                            "field" : "ParentId",
                            "childSObject" : "EntitySubscription",
                            "restrictedDelete" : false,
                            "relationshipName" : "FeedSubscriptionsForEntity",
                            "deprecatedAndHidden" : false,
                            "cascadeDelete" : true
                            },
                            {
                            "field" : "WhatId",
                            "childSObject" : "Event",
                            "restrictedDelete" : false,
                            "relationshipName" : "Events",
                            "deprecatedAndHidden" : false,
                            "cascadeDelete" : true
                            },
                            {
                            "field" : "ParentId",
                            "childSObject" : "FeedComment",
                            "restrictedDelete" : false,
                            "relationshipName" : null,
                            "deprecatedAndHidden" : false,
                            "cascadeDelete" : false
                            },
                            {
                            "field" : "ParentId",
                            "childSObject" : "FeedItem",
                            "restrictedDelete" : false,
                            "relationshipName" : null,
                            "deprecatedAndHidden" : false,
                            "cascadeDelete" : true
                            },
                            {
                            "field" : "WhatId",
                            "childSObject" : "OpenActivity",
                            "restrictedDelete" : false,
                            "relationshipName" : "OpenActivities",
                            "deprecatedAndHidden" : false,
                            "cascadeDelete" : true
                            },
                            {
                            "field" : "TargetObjectId",
                            "childSObject" : "ProcessInstance",
                            "restrictedDelete" : false,
                            "relationshipName" : "ProcessInstances",
                            "deprecatedAndHidden" : false,
                            "cascadeDelete" : true
                            },
                            {
                            "field" : "TargetObjectId",
                            "childSObject" : "ProcessInstanceHistory",
                            "restrictedDelete" : false,
                            "relationshipName" : "ProcessSteps",
                            "deprecatedAndHidden" : false,
                            "cascadeDelete" : false
                            },
                            {
                            "field" : "WhatId",
                            "childSObject" : "Task",
                            "restrictedDelete" : false,
                            "relationshipName" : "Tasks",
                            "deprecatedAndHidden" : false,
                            "cascadeDelete" : true
                            },
                            {
                            "field" : "EntityId",
                            "childSObject" : "TopicAssignment",
                            "restrictedDelete" : false,
                            "relationshipName" : null,
                            "deprecatedAndHidden" : false,
                            "cascadeDelete" : true
                            }
                            ],
	"updateable" : true,
	"urls" : {
		"uiEditTemplate" : "https:\/\/cs1.salesforce.com\/{ID}\/e",
		"sobject" : "\/services\/data\/v29.0\/sobjects\/Case",
		"quickActions" : "\/services\/data\/v29.0\/sobjects\/Case\/quickActions",
		"describe" : "\/services\/data\/v29.0\/sobjects\/Case\/describe",
		"uiDetailTemplate" : "https:\/\/cs1.salesforce.com\/{ID}",
		"rowTemplate" : "\/services\/data\/v29.0\/sobjects\/Case\/{ID}",
		"layouts" : "\/services\/data\/v29.0\/sobjects\/Case\/describe\/layouts",
		"compactLayouts" : "\/services\/data\/v29.0\/sobjects\/Case\/describe\/compactLayouts",
		"uiNewRecord" : "https:\/\/cs1.salesforce.com\/500\/e"
	},
	"mergeable" : false,
	"deletable" : false,
	"label" : "Case",
	"labelPlural" : "Cases",
	"deprecatedAndHidden" : false,
	"feedEnabled" : true,
	"triggerable" : true,
	"layoutable" : true,
	"searchable" : true,
	"queryable" : true,
	"activateable" : false,
	"replicateable" : true
}